[{"timestep":"1d","startTime":"2021-12-09T12:00:00Z","endTime":"2021-12-23T12:00:00Z","intervals":[{"startTime":"2021-12-09T12:00:00Z","values":{"temperature":61.03,"temperatureMin":38.53,"temperatureMax":61.03,"temperatureApparent":61.03,"windSpeed":12.95,"windDirection":174.93,"humidity":97,"pressureSeaLevel":29.52,"uvIndex":1,"weatherCode":1000,"precipitationProbability":0,"precipitationType":0,"sunriseTime":"2021-12-09T13:26:40Z","sunsetTime":"2021-12-09T22:56:40Z","visibility":9.94,"cloudCover":100,"moonPhase":1}},{"startTime":"2021-12-10T12:00:00Z","values":{"temperature":63.43,"temperatureMin":33.62,"temperatureMax":63.43,"temperatureApparent":63.43,"windSpeed":21.59,"windDirection":219.99,"humidity":91.63,"pressureSeaLevel":29.32,"uvIndex":1,"weatherCode":1001,"precipitationProbability":25,"precipitationType":2,"sunriseTime":"2021-12-10T13:28:20Z","sunsetTime":"2021-12-10T22:56:40Z","visibility":9.94,"cloudCover":100,"moonPhase":2}},{"startTime":"2021-12-11T12:00:00Z","values":{"temperature":44.37,"temperatureMin":33.08,"temperatureMax":44.37,"temperatureApparent":44.37,"windSpeed":14.45,"windDirection":240.86,"humidity":67.68,"pressureSeaLevel":30.01,"uvIndex":1,"weatherCode":1000,"precipitationProbability":0,"precipitationType":0,"sunriseTime":"2021-12-11T13:28:20Z","sunsetTime":"2021-12-11T22:56:40Z","visibility":9.94,"cloudCover":79.69,"moonPhase":2}},{"startTime":"2021-12-12T12:00:00Z","values":{"temperature":52.65,"temperatureMin":36.77,"temperatureMax":52.65,"temperatureApparent":52.65,"windSpeed":13.44,"windDirection":191.7,"humidity":55.84,"pressureSeaLevel":30.01,"uvIndex":1,"weatherCode":1000,"precipitationProbability":0,"precipitationType":0,"sunriseTime":"2021-12-12T13:28:20Z","sunsetTime":"2021-12-12T22:56:40Z","visibility":15,"cloudCover":30.09,"moonPhase":2}},{"startTime":"2021-12-13T12:00:00Z","values":{"temperature":61.83,"temperatureMin":40.91,"temperatureMax":61.83,"temperatureApparent":61.83,"windSpeed":17.07,"windDirection":186.22,"humidity":92.68,"pressureSeaLevel":30.01,"uvIndex":1,"weatherCode":1001,"precipitationProbability":0,"precipitationType":0,"sunriseTime":"2021-12-13T13:30:00Z","sunsetTime":"2021-12-13T22:56:40Z","visibility":15,"cloudCover":100,"moonPhase":3}},{"startTime":"2021-12-14T12:00:00Z","values":{"temperature":71.74,"temperatureMin":59.38,"temperatureMax":71.74,"temperatureApparent":71.74,"windSpeed":21.07,"windDirection":199.71,"humidity":88.4,"pressureSeaLevel":29.88,"weatherCode":1001,"precipitationProbability":0,"precipitationType":0,"sunriseTime":"2021-12-14T13:30:00Z","sunsetTime":"2021-12-14T22:56:40Z","visibility":15,"cloudCover":100,"moonPhase":3}},{"startTime":"2021-12-15T12:00:00Z","values":{"temperature":68.77,"temperatureMin":49.77,"temperatureMax":68.77,"temperatureApparent":68.77,"windSpeed":27.56,"windDirection":238.18,"humidity":80.68,"pressureSeaLevel":29.71,"weatherCode":1001,"precipitationProbability":35,"precipitationType":1,"sunriseTime":"2021-12-15T13:30:00Z","sunsetTime":"2021-12-15T22:58:20Z","visibility":15,"cloudCover":100,"moonPhase":3}},{"startTime":"2021-12-16T12:00:00Z","values":{"temperature":53.89,"temperatureMin":36.34,"temperatureMax":53.89,"temperatureApparent":53.89,"windSpeed":11.45,"windDirection":224.77,"humidity":35.24,"pressureSeaLevel":30.1,"weatherCode":1001,"precipitationProbability":0,"precipitationType":2,"sunriseTime":"2021-12-16T13:33:20Z","sunsetTime":"2021-12-16T22:58:20Z","visibility":15,"cloudCover":100,"moonPhase":3}},{"startTime":"2021-12-17T12:00:00Z","values":{"temperature":52.56,"temperatureMin":30.83,"temperatureMax":52.56,"temperatureApparent":52.56,"windSpeed":10.6,"windDirection":163.4,"humidity":40.16,"pressureSeaLevel":30.19,"weatherCode":1001,"precipitationProbability":0,"precipitationType":0,"sunriseTime":"2021-12-17T13:33:20Z","sunsetTime":"2021-12-17T22:58:20Z","visibility":15,"cloudCover":99.54,"moonPhase":4}},{"startTime":"2021-12-18T12:00:00Z","values":{"temperature":40.39,"temperatureMin":30.83,"temperatureMax":40.39,"temperatureApparent":40.39,"windSpeed":10.07,"windDirection":116.08,"humidity":86.69,"pressureSeaLevel":30.12,"weatherCode":1001,"precipitationProbability":10,"precipitationType":2,"sunriseTime":"2021-12-18T13:33:20Z","sunsetTime":"2021-12-18T22:58:20Z","visibility":15,"cloudCover":100,"moonPhase":4}},{"startTime":"2021-12-19T12:00:00Z","values":{"temperature":55.33,"temperatureMin":38.41,"temperatureMax":55.33,"temperatureApparent":55.33,"windSpeed":26.89,"windDirection":157.83,"humidity":97.54,"pressureSeaLevel":29.56,"weatherCode":1001,"precipitationProbability":85,"precipitationType":2,"sunriseTime":"2021-12-19T13:35:00Z","sunsetTime":"2021-12-19T22:58:20Z","visibility":15,"cloudCover":100,"moonPhase":4}},{"startTime":"2021-12-20T12:00:00Z","values":{"temperature":40.46,"temperatureMin":10.02,"temperatureMax":40.46,"temperatureApparent":33.8,"windSpeed":26.89,"windDirection":310.37,"humidity":77.21,"pressureSeaLevel":29.63,"weatherCode":1001,"precipitationProbability":75,"precipitationType":2,"sunriseTime":"2021-12-20T13:35:00Z","sunsetTime":"2021-12-20T22:58:20Z","visibility":15,"cloudCover":100,"moonPhase":4}},{"startTime":"2021-12-21T12:00:00Z","values":{"temperature":23.85,"temperatureMin":10.02,"temperatureMax":23.85,"temperatureApparent":10.44,"windSpeed":18.07,"windDirection":288.2,"humidity":69.75,"pressureSeaLevel":30.46,"weatherCode":1000,"precipitationProbability":0,"precipitationType":0,"sunriseTime":"2021-12-21T13:35:00Z","sunsetTime":"2021-12-21T23:00:00Z","visibility":15,"cloudCover":50.8,"moonPhase":5}},{"startTime":"2021-12-22T12:00:00Z","values":{"temperature":38.79,"temperatureMin":14.36,"temperatureMax":38.79,"temperatureApparent":30.79,"windSpeed":15.75,"windDirection":197.46,"humidity":67.66,"pressureSeaLevel":29.94,"weatherCode":1001,"precipitationProbability":0,"precipitationType":0,"sunriseTime":"2021-12-22T13:35:00Z","sunsetTime":"2021-12-22T23:00:00Z","visibility":15,"cloudCover":100,"moonPhase":5}},{"startTime":"2021-12-23T12:00:00Z","values":{"temperature":45.37,"temperatureMin":29.89,"temperatureMax":45.37,"temperatureApparent":45.37,"windSpeed":11.45,"windDirection":265.15,"humidity":60.91,"pressureSeaLevel":29.94,"weatherCode":1001,"precipitationProbability":0,"precipitationType":0,"sunriseTime":"2021-12-23T13:35:00Z","sunsetTime":"2021-12-23T23:00:00Z","visibility":15,"cloudCover":100,"moonPhase":5}}]},{"timestep":"1h","startTime":"2021-12-09T22:00:00Z","endTime":"2021-12-14T10:00:00Z","intervals":[{"startTime":"2021-12-09T22:00:00Z","values":{"temperature":60.58,"temperatureMin":60.58,"temperatureMax":60.58,"temperatureApparent":60.58,"windSpeed":4.9,"windDirection":275.81,"humidity":45,"pressureSeaLevel":29.69,"uvIndex":0,"weatherCode":1000,"precipitationProbability":0,"precipitationType":0,"sunriseTime":"2021-12-09T13:26:40Z","sunsetTime":"2021-12-09T22:56:40Z","visibility":9.94,"cloudCover":0,"moonPhase":1}},{"startTime":"2021-12-09T23:00:00Z","values":{"temperature":53.28,"temperatureMin":53.28,"temperatureMax":53.28,"temperatureApparent":53.28,"windSpeed":5.55,"windDirection":260.57,"humidity":51.71,"pressureSeaLevel":29.7,"uvIndex":0,"weatherCode":1000,"precipitationProbability":0,"precipitationType":0,"sunriseTime":"2021-12-09T13:26:40Z","sunsetTime":"2021-12-09T22:56:40Z","visibility":9.94,"cloudCover":0,"moonPhase":1}},{"startTime":"2021-12-10T00:00:00Z","values":{"temperature":49.66,"temperatureMin":49.66,"temperatureMax":49.66,"temperatureApparent":49.66,"windSpeed":6.17,"windDirection":308.17,"humidity":61.11,"pressureSeaLevel":29.75,"uvIndex":0,"weatherCode":1101,"precipitationProbability":0,"precipitationType":0,"sunriseTime":"2021-12-09T13:26:40Z","sunsetTime":"2021-12-09T22:56:40Z","visibility":9.94,"cloudCover":48.97,"moonPhase":1}},{"startTime":"2021-12-10T01:00:00Z","values":{"temperature":48.31,"temperatureMin":48.31,"temperatureMax":48.31,"temperatureApparent":48.31,"windSpeed":7.45,"windDirection":341.38,"humidity":65.58,"pressureSeaLevel":29.74,"uvIndex":0,"weatherCode":1000,"precipitationProbability":0,"precipitationType":0,"sunriseTime":"2021-12-09T13:26:40Z","sunsetTime":"2021-12-09T22:56:40Z","visibility":9.94,"cloudCover":7.99,"moonPhase":1}},{"startTime":"2021-12-10T02:00:00Z","values":{"temperature":47.39,"temperatureMin":47.39,"temperatureMax":47.39,"temperatureApparent":47.39,"windSpeed":7.65,"windDirection":4.58,"humidity":58.89,"pressureSeaLevel":29.78,"uvIndex":0,"weatherCode":1100,"precipitationProbability":0,"precipitationType":0,"sunriseTime":"2021-12-09T13:26:40Z","sunsetTime":"2021-12-09T22:56:40Z","visibility":9.94,"cloudCover":14.49,"moonPhase":1}},{"startTime":"2021-12-10T03:00:00Z","values":{"temperature":46.13,"temperatureMin":46.13,"temperatureMax":46.13,"temperatureApparent":46.13,"windSpeed":4.23,"windDirection":40.88,"humidity":55.93,"pressureSeaLevel":29.79,"uvIndex":0,"weatherCode":1001,"precipitationProbability":0,"precipitationType":0,"sunriseTime":"2021-12-09T13:26:40Z","sunsetTime":"2021-12-09T22:56:40Z","visibility":9.94,"cloudCover":100,"moonPhase":1}},{"startTime":"2021-12-10T04:00:00Z","values":{"temperature":43.92,"temperatureMin":43.92,"temperatureMax":43.92,"temperatureApparent":43.92,"windSpeed":5.55,"windDirection":51.37,"humidity":58.31,"pressureSeaLevel":29.78,"uvIndex":0,"weatherCode":1000,"precipitationProbability":0,"precipitationType":0,"sunriseTime":"2021-12-09T13:26:40Z","sunsetTime":"2021-12-09T22:56:40Z","visibility":9.94,"cloudCover":0,"moonPhase":1}},{"startTime":"2021-12-10T05:00:00Z","values":{"temperature":42.13,"temperatureMin":42.13,"temperatureMax":42.13,"temperatureApparent":42.13,"windSpeed":5.23,"windDirection":64.14,"humidity":64.79,"pressureSeaLevel":29.75,"uvIndex":0,"weatherCode":1000,"precipitationProbability":0,"precipitationType":0,"sunriseTime":"2021-12-09T13:26:40Z","sunsetTime":"2021-12-09T22:56:40Z","visibility":9.94,"cloudCover":0,"moonPhase":1}},{"startTime":"2021-12-10T06:00:00Z","values":{"temperature":40.62,"temperatureMin":40.62,"temperatureMax":40.62,"temperatureApparent":40.62,"windSpeed":4.92,"windDirection":64.66,"humidity":69.39,"pressureSeaLevel":29.75,"uvIndex":0,"weatherCode":1000,"precipitationProbability":0,"precipitationType":0,"sunriseTime":"2021-12-10T13:28:20Z","sunsetTime":"2021-12-10T22:56:40Z","visibility":9.94,"cloudCover":6.98,"moonPhase":2}},{"startTime":"2021-12-10T07:00:00Z","values":{"temperature":40.53,"temperatureMin":40.53,"temperatureMax":40.53,"temperatureApparent":40.53,"windSpeed":7.65,"windDirection":62.76,"humidity":72.73,"pressureSeaLevel":29.75,"uvIndex":0,"weatherCode":1000,"precipitationProbability":0,"precipitationType":0,"sunriseTime":"2021-12-10T13:28:20Z","sunsetTime":"2021-12-10T22:56:40Z","visibility":9.94,"cloudCover":0,"moonPhase":2}},{"startTime":"2021-12-10T08:00:00Z","values":{"temperature":40.6,"temperatureMin":40.6,"temperatureMax":40.6,"temperatureApparent":40.6,"windSpeed":9.93,"windDirection":77.96,"humidity":74.59,"pressureSeaLevel":29.72,"uvIndex":0,"weatherCode":1000,"precipitationProbability":0,"precipitationType":0,"sunriseTime":"2021-12-10T13:28:20Z","sunsetTime":"2021-12-10T22:56:40Z","visibility":9.94,"cloudCover":0,"moonPhase":2}},{"startTime":"2021-12-10T09:00:00Z","values":{"temperature":40.68,"temperatureMin":40.68,"temperatureMax":40.68,"temperatureApparent":40.68,"windSpeed":10.78,"windDirection":90.52,"humidity":74.6,"pressureSeaLevel":29.7,"uvIndex":0,"weatherCode":1000,"precipitationProbability":0,"precipitationType":0,"sunriseTime":"2021-12-10T13:28:20Z","sunsetTime":"2021-12-10T22:56:40Z","visibility":9.94,"cloudCover":0,"moonPhase":2}},{"startTime":"2021-12-10T10:00:00Z","values":{"temperature":40.84,"temperatureMin":40.84,"temperatureMax":40.84,"temperatureApparent":40.84,"windSpeed":11.59,"windDirection":86.72,"humidity":76.41,"pressureSeaLevel":29.67,"uvIndex":0,"weatherCode":1000,"precipitationProbability":0,"precipitationType":0,"sunriseTime":"2021-12-10T13:28:20Z","sunsetTime":"2021-12-10T22:56:40Z","visibility":9.94,"cloudCover":0,"moonPhase":2}},{"startTime":"2021-12-10T11:00:00Z","values":{"temperature":40.87,"temperatureMin":40.87,"temperatureMax":40.87,"temperatureApparent":40.87,"windSpeed":12.95,"windDirection":88.92,"humidity":76.8,"pressureSeaLevel":29.62,"uvIndex":0,"weatherCode":1000,"precipitationProbability":0,"precipitationType":0,"sunriseTime":"2021-12-10T13:28:20Z","sunsetTime":"2021-12-10T22:56:40Z","visibility":9.94,"cloudCover":2,"moonPhase":2}},{"startTime":"2021-12-10T12:00:00Z","values":{"temperature":40.69,"temperatureMin":40.69,"temperatureMax":40.69,"temperatureApparent":40.69,"windSpeed":13.24,"windDirection":92.68,"humidity":77.34,"pressureSeaLevel":29.59,"uvIndex":0,"weatherCode":1000,"precipitationProbability":0,"precipitationType":0,"sunriseTime":"2021-12-10T13:28:20Z","sunsetTime":"2021-12-10T22:56:40Z","visibility":9.94,"cloudCover":0,"moonPhase":2}},{"startTime":"2021-12-10T13:00:00Z","values":{"temperature":40.26,"temperatureMin":40.26,"temperatureMax":40.26,"temperatureApparent":40.26,"windSpeed":11.23,"windDirection":94.31,"humidity":80.06,"pressureSeaLevel":29.57,"uvIndex":0,"weatherCode":1000,"precipitationProbability":0,"precipitationType":0,"sunriseTime":"2021-12-10T13:28:20Z","sunsetTime":"2021-12-10T22:56:40Z","visibility":9.94,"cloudCover":3.01,"moonPhase":2}},{"startTime":"2021-12-10T14:00:00Z","values":{"temperature":41.83,"temperatureMin":41.83,"temperatureMax":41.83,"temperatureApparent":41.83,"windSpeed":11.77,"windDirection":98.12,"humidity":83.81,"pressureSeaLevel":29.54,"uvIndex":0,"weatherCode":1001,"precipitationProbability":0,"precipitationType":0,"sunriseTime":"2021-12-10T13:28:20Z","sunsetTime":"2021-12-10T22:56:40Z","visibility":9.94,"cloudCover":99.92,"moonPhase":2}},{"startTime":"2021-12-10T15:00:00Z","values":{"temperature":44.29,"temperatureMin":44.29,"temperatureMax":44.29,"temperatureApparent":44.29,"windSpeed":7.74,"windDirection":113.23,"humidity":89.82,"pressureSeaLevel":29.51,"uvIndex":0,"weatherCode":1001,"precipitationProbability":0,"precipitationType":0,"sunriseTime":"2021-12-10T13:28:20Z","sunsetTime":"2021-12-10T22:56:40Z","visibility":8.6,"cloudCover":100,"moonPhase":2}},{"startTime":"2021-12-10T16:00:00Z","values":{"temperature":51.39,"temperatureMin":51.39,"temperatureMax":51.39,"temperatureApparent":51.39,"windSpeed":6.42,"windDirection":150.68,"humidity":91.63,"pressureSeaLevel":29.48,"uvIndex":0,"weatherCode":1001,"precipitationProbability":0,"precipitationType":0,"sunriseTime":"2021-12-10T13:28:20Z","sunsetTime":"2021-12-10T22:56:40Z","visibility":8.33,"cloudCover":100,"moonPhase":2}},{"startTime":"2021-12-10T17:00:00Z","values":{"temperature":50.52,"temperatureMin":50.52,"temperatureMax":50.52,"temperatureApparent":50.52,"windSpeed":7.54,"windDirection":109.57,"humidity":85.92,"pressureSeaLevel":29.54,"uvIndex":1,"weatherCode":1001,"precipitationProbability":0,"precipitationType":1,"sunriseTime":"2021-12-10T13:28:20Z","sunsetTime":"2021-12-10T22:56:40Z","visibility":9.94,"cloudCover":100,"moonPhase":2}},{"startTime":"2021-12-10T18:00:00Z","values":{"temperature":55.17,"temperatureMin":55.17,"temperatureMax":55.17,"temperatureApparent":55.17,"windSpeed":6.42,"windDirection":124.02,"humidity":81.48,"pressureSeaLevel":29.46,"uvIndex":0,"weatherCode":1001,"precipitationProbability":0,"precipitationType":1,"sunriseTime":"2021-12-10T13:28:20Z","sunsetTime":"2021-12-10T22:56:40Z","visibility":9.94,"cloudCover":100,"moonPhase":2}},{"startTime":"2021-12-10T19:00:00Z","values":{"temperature":58.75,"temperatureMin":58.75,"temperatureMax":58.75,"temperatureApparent":58.75,"windSpeed":8.66,"windDirection":197.11,"humidity":68.87,"pressureSeaLevel":29.42,"uvIndex":1,"weatherCode":1001,"precipitationProbability":15,"precipitationType":1,"sunriseTime":"2021-12-10T13:28:20Z","sunsetTime":"2021-12-10T22:56:40Z","visibility":9.94,"cloudCover":100,"moonPhase":2}},{"startTime":"2021-12-10T20:00:00Z","values":{"temperature":60.01,"temperatureMin":60.01,"temperatureMax":60.01,"temperatureApparent":60.01,"windSpeed":11.19,"windDirection":202.16,"humidity":60.63,"pressureSeaLevel":29.39,"uvIndex":1,"weatherCode":1101,"precipitationProbability":0,"precipitationType":1,"sunriseTime":"2021-12-10T13:28:20Z","sunsetTime":"2021-12-10T22:56:40Z","visibility":9.94,"cloudCover":60.94,"moonPhase":2}},{"startTime":"2021-12-10T21:00:00Z","values":{"temperature":62.58,"temperatureMin":62.58,"temperatureMax":62.58,"temperatureApparent":62.58,"windSpeed":11.9,"windDirection":193.92,"humidity":59.71,"pressureSeaLevel":29.35,"uvIndex":0,"weatherCode":1101,"precipitationProbability":0,"precipitationType":1,"sunriseTime":"2021-12-10T13:28:20Z","sunsetTime":"2021-12-10T22:56:40Z","visibility":9.94,"cloudCover":48.44,"moonPhase":2}},{"startTime":"2021-12-10T22:00:00Z","values":{"temperature":63.43,"temperatureMin":63.43,"temperatureMax":63.43,"temperatureApparent":63.43,"windSpeed":12.55,"windDirection":195.95,"humidity":59.15,"pressureSeaLevel":29.33,"uvIndex":0,"weatherCode":1001,"precipitationProbability":0,"precipitationType":1,"sunriseTime":"2021-12-10T13:28:20Z","sunsetTime":"2021-12-10T22:56:40Z","visibility":9.94,"cloudCover":100,"moonPhase":2}},{"startTime":"2021-12-10T23:00:00Z","values":{"temperature":62.65,"temperatureMin":62.65,"temperatureMax":62.65,"temperatureApparent":62.65,"windSpeed":11.59,"windDirection":191.28,"humidity":61.85,"pressureSeaLevel":29.32,"uvIndex":0,"weatherCode":1001,"precipitationProbability":0,"precipitationType":1,"sunriseTime":"2021-12-10T13:28:20Z","sunsetTime":"2021-12-10T22:56:40Z","visibility":9.94,"cloudCover":100,"moonPhase":2}},{"startTime":"2021-12-11T00:00:00Z","values":{"temperature":62.98,"temperatureMin":62.98,"temperatureMax":62.98,"temperatureApparent":62.98,"windSpeed":11.83,"windDirection":196.3,"humidity":63.45,"pressureSeaLevel":29.32,"uvIndex":0,"weatherCode":1001,"precipitationProbability":0,"precipitationType":1,"sunriseTime":"2021-12-10T13:28:20Z","sunsetTime":"2021-12-10T22:56:40Z","visibility":9.94,"cloudCover":100,"moonPhase":2}},{"startTime":"2021-12-11T01:00:00Z","values":{"temperature":61.79,"temperatureMin":61.79,"temperatureMax":61.79,"temperatureApparent":61.79,"windSpeed":12.93,"windDirection":208.55,"humidity":65.66,"pressureSeaLevel":29.32,"uvIndex":0,"weatherCode":1102,"precipitationProbability":0,"precipitationType":1,"sunriseTime":"2021-12-10T13:28:20Z","sunsetTime":"2021-12-10T22:56:40Z","visibility":9.94,"cloudCover":67.97,"moonPhase":2}},{"startTime":"2021-12-11T02:00:00Z","values":{"temperature":50.79,"temperatureMin":50.79,"temperatureMax":50.79,"temperatureApparent":50.79,"windSpeed":12.21,"windDirection":312.64,"humidity":82.07,"pressureSeaLevel":29.37,"uvIndex":0,"weatherCode":1000,"precipitationProbability":0,"precipitationType":1,"sunriseTime":"2021-12-10T13:28:20Z","sunsetTime":"2021-12-10T22:56:40Z","visibility":9.94,"cloudCover":7.81,"moonPhase":2}},{"startTime":"2021-12-11T03:00:00Z","values":{"temperature":42.03,"temperatureMin":42.03,"temperatureMax":42.03,"temperatureApparent":42.03,"windSpeed":16.44,"windDirection":302.06,"humidity":81.41,"pressureSeaLevel":29.46,"uvIndex":0,"weatherCode":1102,"precipitationProbability":0,"precipitationType":1,"sunriseTime":"2021-12-10T13:28:20Z","sunsetTime":"2021-12-10T22:56:40Z","visibility":9.94,"cloudCover":74.22,"moonPhase":2}},{"startTime":"2021-12-11T04:00:00Z","values":{"temperature":39.25,"temperatureMin":39.25,"temperatureMax":39.25,"temperatureApparent":30.67,"windSpeed":15.52,"windDirection":295.85,"humidity":78.55,"pressureSeaLevel":29.51,"uvIndex":0,"weatherCode":1001,"precipitationProbability":0,"precipitationType":1,"sunriseTime":"2021-12-10T13:28:20Z","sunsetTime":"2021-12-10T22:56:40Z","visibility":9.94,"cloudCover":98.44,"moonPhase":2}},{"startTime":"2021-12-11T05:00:00Z","values":{"temperature":37.65,"temperatureMin":37.65,"temperatureMax":37.65,"temperatureApparent":28.35,"windSpeed":16.44,"windDirection":283.66,"humidity":78.12,"pressureSeaLevel":29.58,"uvIndex":0,"weatherCode":1001,"precipitationProbability":0,"precipitationType":1,"sunriseTime":"2021-12-10T13:28:20Z","sunsetTime":"2021-12-10T22:56:40Z","visibility":9.94,"cloudCover":100,"moonPhase":2}},{"startTime":"2021-12-11T06:00:00Z","values":{"temperature":36.72,"temperatureMin":36.72,"temperatureMax":36.72,"temperatureApparent":26.4,"windSpeed":18.95,"windDirection":283.25,"humidity":73.96,"pressureSeaLevel":29.63,"uvIndex":0,"weatherCode":4000,"precipitationProbability":20,"precipitationType":1,"sunriseTime":"2021-12-11T13:28:20Z","sunsetTime":"2021-12-11T22:56:40Z","visibility":9.94,"cloudCover":100,"moonPhase":2}},{"startTime":"2021-12-11T07:00:00Z","values":{"temperature":35.2,"temperatureMin":35.2,"temperatureMax":35.2,"temperatureApparent":24.03,"windSpeed":20.49,"windDirection":292.45,"humidity":70.19,"pressureSeaLevel":29.7,"uvIndex":0,"weatherCode":5001,"precipitationProbability":25,"precipitationType":2,"sunriseTime":"2021-12-11T13:28:20Z","sunsetTime":"2021-12-11T22:56:40Z","visibility":9.94,"cloudCover":100,"moonPhase":2}},{"startTime":"2021-12-11T08:00:00Z","values":{"temperature":34.32,"temperatureMin":34.32,"temperatureMax":34.32,"temperatureApparent":23,"windSpeed":20,"windDirection":301,"humidity":68.86,"pressureSeaLevel":29.77,"uvIndex":0,"weatherCode":1001,"precipitationProbability":0,"precipitationType":2,"sunriseTime":"2021-12-11T13:28:20Z","sunsetTime":"2021-12-11T22:56:40Z","visibility":9.94,"cloudCover":97.66,"moonPhase":2}},{"startTime":"2021-12-11T09:00:00Z","values":{"temperature":33.62,"temperatureMin":33.62,"temperatureMax":33.62,"temperatureApparent":22.75,"windSpeed":17.67,"windDirection":300.83,"humidity":69.69,"pressureSeaLevel":29.83,"uvIndex":0,"weatherCode":1001,"precipitationProbability":0,"precipitationType":2,"sunriseTime":"2021-12-11T13:28:20Z","sunsetTime":"2021-12-11T22:56:40Z","visibility":9.94,"cloudCover":93.75,"moonPhase":2}},{"startTime":"2021-12-11T10:00:00Z","values":{"temperature":33.62,"temperatureMin":33.62,"temperatureMax":33.62,"temperatureApparent":21.67,"windSpeed":21.59,"windDirection":304.59,"humidity":69.77,"pressureSeaLevel":29.88,"uvIndex":0,"weatherCode":1001,"precipitationProbability":10,"precipitationType":2,"sunriseTime":"2021-12-11T13:28:20Z","sunsetTime":"2021-12-11T22:56:40Z","visibility":9.94,"cloudCover":100,"moonPhase":2}},{"startTime":"2021-12-11T11:00:00Z","values":{"temperature":33.76,"temperatureMin":33.76,"temperatureMax":33.76,"temperatureApparent":22.82,"windSpeed":18.1,"windDirection":308.24,"humidity":67.88,"pressureSeaLevel":29.91,"uvIndex":0,"weatherCode":1001,"precipitationProbability":5,"precipitationType":2,"sunriseTime":"2021-12-11T13:28:20Z","sunsetTime":"2021-12-11T22:56:40Z","visibility":9.94,"cloudCover":96.09,"moonPhase":2}},{"startTime":"2021-12-11T12:00:00Z","values":{"temperature":33.42,"temperatureMin":33.42,"temperatureMax":33.42,"temperatureApparent":23.61,"windSpeed":14.34,"windDirection":309.26,"humidity":68.24,"pressureSeaLevel":29.96,"uvIndex":0,"weatherCode":1001,"precipitationProbability":0,"precipitationType":0,"sunriseTime":"2021-12-11T13:28:20Z","sunsetTime":"2021-12-11T22:56:40Z","visibility":9.94,"cloudCover":92.97,"moonPhase":2}},{"startTime":"2021-12-11T13:00:00Z","values":{"temperature":33.78,"temperatureMin":33.78,"temperatureMax":33.78,"temperatureApparent":24.03,"windSpeed":14.45,"windDirection":308.07,"humidity":65.91,"pressureSeaLevel":30.01,"uvIndex":0,"weatherCode":1001,"precipitationProbability":0,"precipitationType":0,"sunriseTime":"2021-12-11T13:28:20Z","sunsetTime":"2021-12-11T22:56:40Z","visibility":9.94,"cloudCover":79.69,"moonPhase":2}},{"startTime":"2021-12-11T14:00:00Z","values":{"temperature":33.08,"temperatureMin":33.08,"temperatureMax":33.08,"temperatureApparent":24.1,"windSpeed":12.06,"windDirection":302.38,"humidity":67.68,"pressureSeaLevel":30.06,"uvIndex":0,"weatherCode":1000,"precipitationProbability":0,"precipitationType":0,"sunriseTime":"2021-12-11T13:28:20Z","sunsetTime":"2021-12-11T22:56:40Z","visibility":9.94,"cloudCover":5.47,"moonPhase":2}},{"startTime":"2021-12-11T15:00:00Z","values":{"temperature":34.66,"temperatureMin":34.66,"temperatureMax":34.66,"temperatureApparent":26.89,"windSpeed":10.22,"windDirection":296.21,"humidity":64.49,"pressureSeaLevel":30.1,"uvIndex":0,"weatherCode":1000,"precipitationProbability":0,"precipitationType":0,"sunriseTime":"2021-12-11T13:28:20Z","sunsetTime":"2021-12-11T22:56:40Z","visibility":9.94,"cloudCover":0,"moonPhase":2}},{"startTime":"2021-12-11T16:00:00Z","values":{"temperature":37.08,"temperatureMin":37.08,"temperatureMax":37.08,"temperatureApparent":30.07,"windSpeed":9.82,"windDirection":289.37,"humidity":60.01,"pressureSeaLevel":30.12,"uvIndex":0,"weatherCode":1000,"precipitationProbability":0,"precipitationType":0,"sunriseTime":"2021-12-11T13:28:20Z","sunsetTime":"2021-12-11T22:56:40Z","visibility":9.94,"cloudCover":0,"moonPhase":2}},{"startTime":"2021-12-11T17:00:00Z","values":{"temperature":39.6,"temperatureMin":39.6,"temperatureMax":39.6,"temperatureApparent":33.04,"windSpeed":10.13,"windDirection":278.77,"humidity":56.28,"pressureSeaLevel":30.13,"uvIndex":1,"weatherCode":1000,"precipitationProbability":0,"precipitationType":0,"sunriseTime":"2021-12-11T13:28:20Z","sunsetTime":"2021-12-11T22:56:40Z","visibility":9.94,"cloudCover":0,"moonPhase":2}},{"startTime":"2021-12-11T18:00:00Z","values":{"temperature":41.67,"temperatureMin":41.67,"temperatureMax":41.67,"temperatureApparent":41.67,"windSpeed":10.51,"windDirection":267.5,"humidity":52.21,"pressureSeaLevel":30.12,"uvIndex":1,"weatherCode":1000,"precipitationProbability":0,"precipitationType":0,"sunriseTime":"2021-12-11T13:28:20Z","sunsetTime":"2021-12-11T22:56:40Z","visibility":9.94,"cloudCover":0,"moonPhase":2}},{"startTime":"2021-12-11T19:00:00Z","values":{"temperature":43.2,"temperatureMin":43.2,"temperatureMax":43.2,"temperatureApparent":43.2,"windSpeed":10.72,"windDirection":263.23,"humidity":48.68,"pressureSeaLevel":30.12,"uvIndex":1,"weatherCode":1000,"precipitationProbability":0,"precipitationType":0,"sunriseTime":"2021-12-11T13:28:20Z","sunsetTime":"2021-12-11T22:56:40Z","visibility":9.94,"cloudCover":0,"moonPhase":2}},{"startTime":"2021-12-11T20:00:00Z","values":{"temperature":44.22,"temperatureMin":44.22,"temperatureMax":44.22,"temperatureApparent":44.22,"windSpeed":10.65,"windDirection":264.71,"humidity":45.5,"pressureSeaLevel":30.11,"uvIndex":1,"weatherCode":1000,"precipitationProbability":0,"precipitationType":0,"sunriseTime":"2021-12-11T13:28:20Z","sunsetTime":"2021-12-11T22:56:40Z","visibility":9.94,"cloudCover":0,"moonPhase":2}},{"startTime":"2021-12-11T21:00:00Z","values":{"temperature":44.37,"temperatureMin":44.37,"temperatureMax":44.37,"temperatureApparent":44.37,"windSpeed":10.29,"windDirection":263.21,"humidity":43.52,"pressureSeaLevel":30.11,"uvIndex":0,"weatherCode":1000,"precipitationProbability":0,"precipitationType":0,"sunriseTime":"2021-12-11T13:28:20Z","sunsetTime":"2021-12-11T22:56:40Z","visibility":9.94,"cloudCover":0,"moonPhase":2}},{"startTime":"2021-12-11T22:00:00Z","values":{"temperature":43.54,"temperatureMin":43.54,"temperatureMax":43.54,"temperatureApparent":43.54,"windSpeed":7.78,"windDirection":254.88,"humidity":44.13,"pressureSeaLevel":30.1,"uvIndex":0,"weatherCode":1000,"precipitationProbability":0,"precipitationType":0,"sunriseTime":"2021-12-11T13:28:20Z","sunsetTime":"2021-12-11T22:56:40Z","visibility":9.94,"cloudCover":0,"moonPhase":2}},{"startTime":"2021-12-11T23:00:00Z","values":{"temperature":39.51,"temperatureMin":39.51,"temperatureMax":39.51,"temperatureApparent":35.89,"windSpeed":4.94,"windDirection":241.01,"humidity":49.57,"pressureSeaLevel":30.11,"uvIndex":0,"weatherCode":1000,"precipitationProbability":0,"precipitationType":0,"sunriseTime":"2021-12-11T13:28:20Z","sunsetTime":"2021-12-11T22:56:40Z","visibility":9.94,"cloudCover":0,"moonPhase":2}},{"startTime":"2021-12-12T00:00:00Z","values":{"temperature":37.54,"temperatureMin":37.54,"temperatureMax":37.54,"temperatureApparent":32.95,"windSpeed":5.77,"windDirection":224.87,"humidity":53.08,"pressureSeaLevel":30.12,"uvIndex":0,"weatherCode":1000,"precipitationProbability":0,"precipitationType":0,"sunriseTime":"2021-12-11T13:28:20Z","sunsetTime":"2021-12-11T22:56:40Z","visibility":9.94,"cloudCover":0,"moonPhase":2}},{"startTime":"2021-12-12T01:00:00Z","values":{"temperature":36.77,"temperatureMin":36.77,"temperatureMax":36.77,"temperatureApparent":31.28,"windSpeed":6.87,"windDirection":212.79,"humidity":53.8,"pressureSeaLevel":30.13,"uvIndex":0,"weatherCode":1000,"precipitationProbability":0,"precipitationType":0,"sunriseTime":"2021-12-11T13:28:20Z","sunsetTime":"2021-12-11T22:56:40Z","visibility":9.94,"cloudCover":0,"moonPhase":2}},{"startTime":"2021-12-12T02:00:00Z","values":{"temperature":36.45,"temperatureMin":36.45,"temperatureMax":36.45,"temperatureApparent":30.38,"windSpeed":7.72,"windDirection":211.74,"humidity":54.54,"pressureSeaLevel":30.14,"uvIndex":0,"weatherCode":1000,"precipitationProbability":0,"precipitationType":0,"sunriseTime":"2021-12-11T13:28:20Z","sunsetTime":"2021-12-11T22:56:40Z","visibility":9.94,"cloudCover":2.34,"moonPhase":2}},{"startTime":"2021-12-12T03:00:00Z","values":{"temperature":36.19,"temperatureMin":36.19,"temperatureMax":36.19,"temperatureApparent":29.73,"windSpeed":8.3,"windDirection":209.91,"humidity":55.52,"pressureSeaLevel":30.15,"uvIndex":0,"weatherCode":1000,"precipitationProbability":0,"precipitationType":0,"sunriseTime":"2021-12-11T13:28:20Z","sunsetTime":"2021-12-11T22:56:40Z","visibility":9.94,"cloudCover":0,"moonPhase":2}},{"startTime":"2021-12-12T04:00:00Z","values":{"temperature":35.83,"temperatureMin":35.83,"temperatureMax":35.83,"temperatureApparent":29.23,"windSpeed":8.48,"windDirection":209.97,"humidity":56.63,"pressureSeaLevel":30.15,"uvIndex":0,"weatherCode":1000,"precipitationProbability":0,"precipitationType":0,"sunriseTime":"2021-12-11T13:28:20Z","sunsetTime":"2021-12-11T22:56:40Z","visibility":9.94,"cloudCover":0,"moonPhase":2}},{"startTime":"2021-12-12T05:00:00Z","values":{"temperature":35.44,"temperatureMin":35.44,"temperatureMax":35.44,"temperatureApparent":28.78,"windSpeed":8.39,"windDirection":209.65,"humidity":57.4,"pressureSeaLevel":30.15,"uvIndex":0,"weatherCode":1000,"precipitationProbability":0,"precipitationType":0,"sunriseTime":"2021-12-11T13:28:20Z","sunsetTime":"2021-12-11T22:56:40Z","visibility":9.94,"cloudCover":0,"moonPhase":2}},{"startTime":"2021-12-12T06:00:00Z","values":{"temperature":35.13,"temperatureMin":35.13,"temperatureMax":35.13,"temperatureApparent":28.35,"windSpeed":8.5,"windDirection":208.26,"humidity":57.27,"pressureSeaLevel":30.16,"uvIndex":0,"weatherCode":1000,"precipitationProbability":0,"precipitationType":0,"sunriseTime":"2021-12-12T13:28:20Z","sunsetTime":"2021-12-12T22:56:40Z","visibility":9.94,"cloudCover":0,"moonPhase":2}},{"startTime":"2021-12-12T07:00:00Z","values":{"temperature":34.84,"temperatureMin":34.84,"temperatureMax":34.84,"temperatureApparent":27.79,"windSpeed":8.88,"windDirection":207.04,"humidity":57.15,"pressureSeaLevel":30.16,"uvIndex":0,"weatherCode":1000,"precipitationProbability":0,"precipitationType":0,"sunriseTime":"2021-12-12T13:28:20Z","sunsetTime":"2021-12-12T22:56:40Z","visibility":9.94,"cloudCover":0,"moonPhase":2}},{"startTime":"2021-12-12T08:00:00Z","values":{"temperature":34.97,"temperatureMin":34.97,"temperatureMax":34.97,"temperatureApparent":27.46,"windSpeed":9.84,"windDirection":203.63,"humidity":55.44,"pressureSeaLevel":30.16,"uvIndex":0,"weatherCode":1000,"precipitationProbability":0,"precipitationType":0,"sunriseTime":"2021-12-12T13:28:20Z","sunsetTime":"2021-12-12T22:56:40Z","visibility":9.94,"cloudCover":0,"moonPhase":2}},{"startTime":"2021-12-12T09:00:00Z","values":{"temperature":35.38,"temperatureMin":35.38,"temperatureMax":35.38,"temperatureApparent":27.77,"windSpeed":10.25,"windDirection":203.82,"humidity":52.54,"pressureSeaLevel":30.15,"uvIndex":0,"weatherCode":1000,"precipitationProbability":0,"precipitationType":0,"sunriseTime":"2021-12-12T13:28:20Z","sunsetTime":"2021-12-12T22:56:40Z","visibility":9.94,"cloudCover":0,"moonPhase":2}},{"startTime":"2021-12-12T10:00:00Z","values":{"temperature":35.78,"temperatureMin":35.78,"temperatureMax":35.78,"temperatureApparent":27.97,"windSpeed":10.89,"windDirection":204.73,"humidity":49.74,"pressureSeaLevel":30.15,"uvIndex":0,"weatherCode":1000,"precipitationProbability":0,"precipitationType":0,"sunriseTime":"2021-12-12T13:28:20Z","sunsetTime":"2021-12-12T22:56:40Z","visibility":9.94,"cloudCover":0,"moonPhase":2}},{"startTime":"2021-12-12T11:00:00Z","values":{"temperature":36.1,"temperatureMin":36.1,"temperatureMax":36.1,"temperatureApparent":28.29,"windSpeed":11.07,"windDirection":203.98,"humidity":48.34,"pressureSeaLevel":30.14,"uvIndex":0,"weatherCode":1000,"precipitationProbability":0,"precipitationType":0,"sunriseTime":"2021-12-12T13:28:20Z","sunsetTime":"2021-12-12T22:56:40Z","visibility":9.94,"cloudCover":0,"moonPhase":2}},{"startTime":"2021-12-12T12:00:00Z","values":{"temperature":36.52,"temperatureMin":36.52,"temperatureMax":36.52,"temperatureApparent":28.42,"windSpeed":12.06,"windDirection":204.16,"humidity":47.57,"pressureSeaLevel":30.14,"uvIndex":0,"weatherCode":1000,"precipitationProbability":0,"precipitationType":0,"sunriseTime":"2021-12-12T13:28:20Z","sunsetTime":"2021-12-12T22:56:40Z","visibility":9.94,"cloudCover":0,"moonPhase":2}},{"startTime":"2021-12-12T13:00:00Z","values":{"temperature":36.77,"temperatureMin":36.77,"temperatureMax":36.77,"temperatureApparent":28.63,"windSpeed":12.24,"windDirection":204.58,"humidity":47.74,"pressureSeaLevel":30.15,"uvIndex":0,"weatherCode":1000,"precipitationProbability":0,"precipitationType":0,"sunriseTime":"2021-12-12T13:28:20Z","sunsetTime":"2021-12-12T22:56:40Z","visibility":9.94,"cloudCover":0.78,"moonPhase":2}},{"startTime":"2021-12-12T14:00:00Z","values":{"temperature":37.11,"temperatureMin":37.11,"temperatureMax":37.11,"temperatureApparent":29.01,"windSpeed":12.46,"windDirection":203.75,"humidity":49.13,"pressureSeaLevel":30.15,"uvIndex":0,"weatherCode":1000,"precipitationProbability":0,"precipitationType":0,"sunriseTime":"2021-12-12T13:28:20Z","sunsetTime":"2021-12-12T22:56:40Z","visibility":9.94,"cloudCover":3.91,"moonPhase":2}},{"startTime":"2021-12-12T15:00:00Z","values":{"temperature":39.74,"temperatureMin":39.74,"temperatureMax":39.74,"temperatureApparent":33.1,"windSpeed":10.45,"windDirection":202.58,"humidity":49.8,"pressureSeaLevel":30.15,"uvIndex":0,"weatherCode":1000,"precipitationProbability":0,"precipitationType":0,"sunriseTime":"2021-12-12T13:28:20Z","sunsetTime":"2021-12-12T22:56:40Z","visibility":9.94,"cloudCover":7.81,"moonPhase":2}},{"startTime":"2021-12-12T16:00:00Z","values":{"temperature":42.75,"temperatureMin":42.75,"temperatureMax":42.75,"temperatureApparent":42.75,"windSpeed":11.81,"windDirection":202.85,"humidity":48.01,"pressureSeaLevel":30.16,"uvIndex":1,"weatherCode":1000,"precipitationProbability":0,"precipitationType":0,"sunriseTime":"2021-12-12T13:28:20Z","sunsetTime":"2021-12-12T22:56:40Z","visibility":9.94,"cloudCover":7.81,"moonPhase":2}},{"startTime":"2021-12-12T17:00:00Z","values":{"temperature":45.72,"temperatureMin":45.72,"temperatureMax":45.72,"temperatureApparent":45.72,"windSpeed":12.75,"windDirection":199.24,"humidity":44.7,"pressureSeaLevel":30.14,"uvIndex":1,"weatherCode":1000,"precipitationProbability":0,"precipitationType":0,"sunriseTime":"2021-12-12T13:28:20Z","sunsetTime":"2021-12-12T22:56:40Z","visibility":9.94,"cloudCover":6.25,"moonPhase":2}},{"startTime":"2021-12-12T18:00:00Z","values":{"temperature":48.33,"temperatureMin":48.33,"temperatureMax":48.33,"temperatureApparent":48.33,"windSpeed":12.75,"windDirection":197.97,"humidity":42.2,"pressureSeaLevel":30.1,"uvIndex":1,"weatherCode":1000,"precipitationProbability":0,"precipitationType":0,"sunriseTime":"2021-12-12T13:28:20Z","sunsetTime":"2021-12-12T22:56:40Z","visibility":9.94,"cloudCover":0,"moonPhase":2}},{"startTime":"2021-12-12T19:00:00Z","values":{"temperature":50.5,"temperatureMin":50.5,"temperatureMax":50.5,"temperatureApparent":50.5,"windSpeed":12.33,"windDirection":196.43,"humidity":40.66,"pressureSeaLevel":30.06,"uvIndex":1,"weatherCode":1000,"precipitationProbability":0,"precipitationType":0,"sunriseTime":"2021-12-12T13:28:20Z","sunsetTime":"2021-12-12T22:56:40Z","visibility":9.94,"cloudCover":0,"moonPhase":2}},{"startTime":"2021-12-12T20:00:00Z","values":{"temperature":52.29,"temperatureMin":52.29,"temperatureMax":52.29,"temperatureApparent":52.29,"windSpeed":13.06,"windDirection":194.21,"humidity":37.29,"pressureSeaLevel":30.03,"uvIndex":1,"weatherCode":1000,"precipitationProbability":0,"precipitationType":0,"sunriseTime":"2021-12-12T13:28:20Z","sunsetTime":"2021-12-12T22:56:40Z","visibility":10.37,"cloudCover":0.1,"moonPhase":2}},{"startTime":"2021-12-12T21:00:00Z","values":{"temperature":52.65,"temperatureMin":52.65,"temperatureMax":52.65,"temperatureApparent":52.65,"windSpeed":12.5,"windDirection":189.36,"humidity":37.18,"pressureSeaLevel":30.01,"uvIndex":0,"weatherCode":1000,"precipitationProbability":0,"precipitationType":0,"sunriseTime":"2021-12-12T13:28:20Z","sunsetTime":"2021-12-12T22:56:40Z","visibility":10.79,"cloudCover":0.45,"moonPhase":2}},{"startTime":"2021-12-12T22:00:00Z","values":{"temperature":51.53,"temperatureMin":51.53,"temperatureMax":51.53,"temperatureApparent":51.53,"windSpeed":12.91,"windDirection":192.75,"humidity":37.5,"pressureSeaLevel":30.02,"uvIndex":0,"weatherCode":1000,"precipitationProbability":0,"precipitationType":0,"sunriseTime":"2021-12-12T13:28:20Z","sunsetTime":"2021-12-12T22:56:40Z","visibility":11.21,"cloudCover":0.86,"moonPhase":2}},{"startTime":"2021-12-12T23:00:00Z","values":{"temperature":49.33,"temperatureMin":49.33,"temperatureMax":49.33,"temperatureApparent":49.33,"windSpeed":12.59,"windDirection":193.44,"humidity":37.44,"pressureSeaLevel":30.03,"uvIndex":0,"weatherCode":1000,"precipitationProbability":0,"precipitationType":0,"sunriseTime":"2021-12-12T13:28:20Z","sunsetTime":"2021-12-12T22:56:40Z","visibility":11.63,"cloudCover":1.28,"moonPhase":2}},{"startTime":"2021-12-13T00:00:00Z","values":{"temperature":47.89,"temperatureMin":47.89,"temperatureMax":47.89,"temperatureApparent":47.89,"windSpeed":12.3,"windDirection":190.23,"humidity":39.37,"pressureSeaLevel":30.04,"uvIndex":0,"weatherCode":1000,"precipitationProbability":0,"precipitationType":0,"sunriseTime":"2021-12-12T13:28:20Z","sunsetTime":"2021-12-12T22:56:40Z","visibility":12.05,"cloudCover":1.4,"moonPhase":2}},{"startTime":"2021-12-13T01:00:00Z","values":{"temperature":47.07,"temperatureMin":47.07,"temperatureMax":47.07,"temperatureApparent":47.07,"windSpeed":13.04,"windDirection":188.63,"humidity":41.22,"pressureSeaLevel":30.06,"uvIndex":0,"weatherCode":1000,"precipitationProbability":0,"precipitationType":0,"sunriseTime":"2021-12-12T13:28:20Z","sunsetTime":"2021-12-12T22:56:40Z","visibility":12.47,"cloudCover":11.5,"moonPhase":2}},{"startTime":"2021-12-13T02:00:00Z","values":{"temperature":46.47,"temperatureMin":46.47,"temperatureMax":46.47,"temperatureApparent":46.47,"windSpeed":13.4,"windDirection":189.47,"humidity":42.44,"pressureSeaLevel":30.07,"uvIndex":0,"weatherCode":1100,"precipitationProbability":0,"precipitationType":0,"sunriseTime":"2021-12-12T13:28:20Z","sunsetTime":"2021-12-12T22:56:40Z","visibility":12.9,"cloudCover":30.09,"moonPhase":2}},{"startTime":"2021-12-13T03:00:00Z","values":{"temperature":45.86,"temperatureMin":45.86,"temperatureMax":45.86,"temperatureApparent":45.86,"windSpeed":13.44,"windDirection":189.84,"humidity":43.28,"pressureSeaLevel":30.07,"uvIndex":0,"weatherCode":1100,"precipitationProbability":0,"precipitationType":0,"sunriseTime":"2021-12-12T13:28:20Z","sunsetTime":"2021-12-12T22:56:40Z","visibility":13.31,"cloudCover":16.5,"moonPhase":2}},{"startTime":"2021-12-13T04:00:00Z","values":{"temperature":45.18,"temperatureMin":45.18,"temperatureMax":45.18,"temperatureApparent":45.18,"windSpeed":12.75,"windDirection":188.74,"humidity":44.56,"pressureSeaLevel":30.07,"uvIndex":0,"weatherCode":1000,"precipitationProbability":0,"precipitationType":0,"sunriseTime":"2021-12-12T13:28:20Z","sunsetTime":"2021-12-12T22:56:40Z","visibility":13.74,"cloudCover":5.24,"moonPhase":2}},{"startTime":"2021-12-13T05:00:00Z","values":{"temperature":44.56,"temperatureMin":44.56,"temperatureMax":44.56,"temperatureApparent":44.56,"windSpeed":12.77,"windDirection":187.89,"humidity":46.17,"pressureSeaLevel":30.08,"uvIndex":0,"weatherCode":1000,"precipitationProbability":0,"precipitationType":0,"sunriseTime":"2021-12-12T13:28:20Z","sunsetTime":"2021-12-12T22:56:40Z","visibility":14.16,"cloudCover":4.68,"moonPhase":2}},{"startTime":"2021-12-13T06:00:00Z","values":{"temperature":43.9,"temperatureMin":43.9,"temperatureMax":43.9,"temperatureApparent":43.9,"windSpeed":12.55,"windDirection":187.84,"humidity":48.12,"pressureSeaLevel":30.08,"uvIndex":0,"weatherCode":1000,"precipitationProbability":0,"precipitationType":0,"sunriseTime":"2021-12-13T13:30:00Z","sunsetTime":"2021-12-13T22:56:40Z","visibility":14.58,"cloudCover":4.25,"moonPhase":3}},{"startTime":"2021-12-13T07:00:00Z","values":{"temperature":43.27,"temperatureMin":43.27,"temperatureMax":43.27,"temperatureApparent":43.27,"windSpeed":11.5,"windDirection":184.64,"humidity":50.15,"pressureSeaLevel":30.08,"uvIndex":0,"weatherCode":1000,"precipitationProbability":0,"precipitationType":0,"sunriseTime":"2021-12-13T13:30:00Z","sunsetTime":"2021-12-13T22:56:40Z","visibility":15,"cloudCover":0,"moonPhase":3}},{"startTime":"2021-12-13T08:00:00Z","values":{"temperature":43.09,"temperatureMin":43.09,"temperatureMax":43.09,"temperatureApparent":43.09,"windSpeed":10.94,"windDirection":184.32,"humidity":50.86,"pressureSeaLevel":30.08,"uvIndex":0,"weatherCode":1000,"precipitationProbability":0,"precipitationType":0,"sunriseTime":"2021-12-13T13:30:00Z","sunsetTime":"2021-12-13T22:56:40Z","visibility":15,"cloudCover":3,"moonPhase":3}},{"startTime":"2021-12-13T09:00:00Z","values":{"temperature":42.24,"temperatureMin":42.24,"temperatureMax":42.24,"temperatureApparent":42.24,"windSpeed":10.47,"windDirection":182.84,"humidity":53.08,"pressureSeaLevel":30.09,"uvIndex":0,"weatherCode":1000,"precipitationProbability":0,"precipitationType":0,"sunriseTime":"2021-12-13T13:30:00Z","sunsetTime":"2021-12-13T22:56:40Z","visibility":15,"cloudCover":1.98,"moonPhase":3}},{"startTime":"2021-12-13T10:00:00Z","values":{"temperature":41.25,"temperatureMin":41.25,"temperatureMax":41.25,"temperatureApparent":41.25,"windSpeed":9.91,"windDirection":180.02,"humidity":55.43,"pressureSeaLevel":30.08,"uvIndex":0,"weatherCode":1000,"precipitationProbability":0,"precipitationType":0,"sunriseTime":"2021-12-13T13:30:00Z","sunsetTime":"2021-12-13T22:56:40Z","visibility":15,"cloudCover":1.45,"moonPhase":3}},{"startTime":"2021-12-13T11:00:00Z","values":{"temperature":41.09,"temperatureMin":41.09,"temperatureMax":41.09,"temperatureApparent":41.09,"windSpeed":9.62,"windDirection":177.58,"humidity":55.84,"pressureSeaLevel":30.08,"uvIndex":0,"weatherCode":1000,"precipitationProbability":0,"precipitationType":0,"sunriseTime":"2021-12-13T13:30:00Z","sunsetTime":"2021-12-13T22:56:40Z","visibility":15,"cloudCover":2.77,"moonPhase":3}},{"startTime":"2021-12-13T12:00:00Z","values":{"temperature":41.05,"temperatureMin":41.05,"temperatureMax":41.05,"temperatureApparent":41.05,"windSpeed":9.33,"windDirection":175.96,"humidity":56.1,"pressureSeaLevel":30.08,"uvIndex":0,"weatherCode":1000,"precipitationProbability":0,"precipitationType":0,"sunriseTime":"2021-12-13T13:30:00Z","sunsetTime":"2021-12-13T22:56:40Z","visibility":15,"cloudCover":4.32,"moonPhase":3}},{"startTime":"2021-12-13T13:00:00Z","values":{"temperature":40.91,"temperatureMin":40.91,"temperatureMax":40.91,"temperatureApparent":39.36,"windSpeed":9.31,"windDirection":175.33,"humidity":57,"pressureSeaLevel":30.1,"uvIndex":0,"weatherCode":1000,"precipitationProbability":0,"precipitationType":0,"sunriseTime":"2021-12-13T13:30:00Z","sunsetTime":"2021-12-13T22:56:40Z","visibility":15,"cloudCover":8.2,"moonPhase":3}},{"startTime":"2021-12-13T14:00:00Z","values":{"temperature":41.58,"temperatureMin":41.58,"temperatureMax":41.58,"temperatureApparent":41.58,"windSpeed":9.75,"windDirection":176.53,"humidity":56.59,"pressureSeaLevel":30.12,"uvIndex":0,"weatherCode":1100,"precipitationProbability":0,"precipitationType":0,"sunriseTime":"2021-12-13T13:30:00Z","sunsetTime":"2021-12-13T22:56:40Z","visibility":15,"cloudCover":31.64,"moonPhase":3}},{"startTime":"2021-12-13T15:00:00Z","values":{"temperature":45.88,"temperatureMin":45.88,"temperatureMax":45.88,"temperatureApparent":45.88,"windSpeed":11.83,"windDirection":185.05,"humidity":50.32,"pressureSeaLevel":30.12,"uvIndex":0,"weatherCode":1100,"precipitationProbability":0,"precipitationType":0,"sunriseTime":"2021-12-13T13:30:00Z","sunsetTime":"2021-12-13T22:56:40Z","visibility":15,"cloudCover":25.48,"moonPhase":3}},{"startTime":"2021-12-13T16:00:00Z","values":{"temperature":50.54,"temperatureMin":50.54,"temperatureMax":50.54,"temperatureApparent":50.54,"windSpeed":14.79,"windDirection":192.43,"humidity":43.35,"pressureSeaLevel":30.12,"uvIndex":1,"weatherCode":1100,"precipitationProbability":0,"precipitationType":0,"sunriseTime":"2021-12-13T13:30:00Z","sunsetTime":"2021-12-13T22:56:40Z","visibility":15,"cloudCover":21.28,"moonPhase":3}},{"startTime":"2021-12-13T17:00:00Z","values":{"temperature":54.43,"temperatureMin":54.43,"temperatureMax":54.43,"temperatureApparent":54.43,"windSpeed":16.11,"windDirection":195.69,"humidity":38.51,"pressureSeaLevel":30.1,"uvIndex":1,"weatherCode":1100,"precipitationProbability":0,"precipitationType":0,"sunriseTime":"2021-12-13T13:30:00Z","sunsetTime":"2021-12-13T22:56:40Z","visibility":15,"cloudCover":26.6,"moonPhase":3}},{"startTime":"2021-12-13T18:00:00Z","values":{"temperature":57.6,"temperatureMin":57.6,"temperatureMax":57.6,"temperatureApparent":57.6,"windSpeed":16.31,"windDirection":195.18,"humidity":35.45,"pressureSeaLevel":30.07,"uvIndex":1,"weatherCode":1101,"precipitationProbability":0,"precipitationType":0,"sunriseTime":"2021-12-13T13:30:00Z","sunsetTime":"2021-12-13T22:56:40Z","visibility":15,"cloudCover":38.38,"moonPhase":3}},{"startTime":"2021-12-13T19:00:00Z","values":{"temperature":60.49,"temperatureMin":60.49,"temperatureMax":60.49,"temperatureApparent":60.49,"windSpeed":17.07,"windDirection":195.94,"humidity":33.16,"pressureSeaLevel":30.04,"uvIndex":1,"weatherCode":1001,"precipitationProbability":0,"precipitationType":0,"sunriseTime":"2021-12-13T13:30:00Z","sunsetTime":"2021-12-13T22:56:40Z","visibility":15,"cloudCover":79.21,"moonPhase":3}},{"startTime":"2021-12-13T20:00:00Z","values":{"temperature":61.83,"temperatureMin":61.83,"temperatureMax":61.83,"temperatureApparent":61.83,"windSpeed":16.82,"windDirection":194.03,"humidity":32.95,"pressureSeaLevel":30.01,"uvIndex":1,"weatherCode":1001,"precipitationProbability":0,"precipitationType":0,"sunriseTime":"2021-12-13T13:30:00Z","sunsetTime":"2021-12-13T22:56:40Z","visibility":15,"cloudCover":81.36,"moonPhase":3}},{"startTime":"2021-12-13T21:00:00Z","values":{"temperature":61.34,"temperatureMin":61.34,"temperatureMax":61.34,"temperatureApparent":61.34,"windSpeed":15.55,"windDirection":190.57,"humidity":35.22,"pressureSeaLevel":30.01,"uvIndex":0,"weatherCode":1001,"precipitationProbability":0,"precipitationType":0,"sunriseTime":"2021-12-13T13:30:00Z","sunsetTime":"2021-12-13T22:56:40Z","visibility":15,"cloudCover":87.49,"moonPhase":3}},{"startTime":"2021-12-13T22:00:00Z","values":{"temperature":59.49,"temperatureMin":59.49,"temperatureMax":59.49,"temperatureApparent":59.49,"windSpeed":14.97,"windDirection":185.34,"humidity":38.41,"pressureSeaLevel":30.02,"uvIndex":0,"weatherCode":1001,"precipitationProbability":0,"precipitationType":0,"sunriseTime":"2021-12-13T13:30:00Z","sunsetTime":"2021-12-13T22:56:40Z","visibility":15,"cloudCover":86.06,"moonPhase":3}},{"startTime":"2021-12-13T23:00:00Z","values":{"temperature":56.97,"temperatureMin":56.97,"temperatureMax":56.97,"temperatureApparent":56.97,"windSpeed":13.98,"windDirection":183.67,"humidity":42.87,"pressureSeaLevel":30.03,"uvIndex":0,"weatherCode":1001,"precipitationProbability":0,"precipitationType":0,"sunriseTime":"2021-12-13T13:30:00Z","sunsetTime":"2021-12-13T22:56:40Z","visibility":15,"cloudCover":88.8,"moonPhase":3}},{"startTime":"2021-12-14T00:00:00Z","values":{"temperature":55.24,"temperatureMin":55.24,"temperatureMax":55.24,"temperatureApparent":55.24,"windSpeed":13.69,"windDirection":181.49,"humidity":47.79,"pressureSeaLevel":30.05,"uvIndex":0,"weatherCode":1001,"precipitationProbability":0,"precipitationType":0,"sunriseTime":"2021-12-13T13:30:00Z","sunsetTime":"2021-12-13T22:56:40Z","visibility":15,"cloudCover":90.67,"moonPhase":3}},{"startTime":"2021-12-14T01:00:00Z","values":{"temperature":55.08,"temperatureMin":55.08,"temperatureMax":55.08,"temperatureApparent":55.08,"windSpeed":14.47,"windDirection":184.41,"humidity":48.74,"pressureSeaLevel":30.06,"uvIndex":0,"weatherCode":1001,"precipitationProbability":0,"precipitationType":0,"sunriseTime":"2021-12-13T13:30:00Z","sunsetTime":"2021-12-13T22:56:40Z","visibility":15,"cloudCover":100,"moonPhase":3}},{"startTime":"2021-12-14T02:00:00Z","values":{"temperature":54.43,"temperatureMin":54.43,"temperatureMax":54.43,"temperatureApparent":54.43,"windSpeed":14.92,"windDirection":182.71,"humidity":49.45,"pressureSeaLevel":30.07,"uvIndex":0,"weatherCode":1001,"precipitationProbability":0,"precipitationType":0,"sunriseTime":"2021-12-13T13:30:00Z","sunsetTime":"2021-12-13T22:56:40Z","visibility":15,"cloudCover":100,"moonPhase":3}},{"startTime":"2021-12-14T03:00:00Z","values":{"temperature":54.21,"temperatureMin":54.21,"temperatureMax":54.21,"temperatureApparent":54.21,"windSpeed":15.39,"windDirection":182.38,"humidity":50.07,"pressureSeaLevel":30.07,"uvIndex":0,"weatherCode":1001,"precipitationProbability":0,"precipitationType":0,"sunriseTime":"2021-12-13T13:30:00Z","sunsetTime":"2021-12-13T22:56:40Z","visibility":15,"cloudCover":100,"moonPhase":3}},{"startTime":"2021-12-14T04:00:00Z","values":{"temperature":53.49,"temperatureMin":53.49,"temperatureMax":53.49,"temperatureApparent":53.49,"windSpeed":15.21,"windDirection":181.82,"humidity":52.53,"pressureSeaLevel":30.07,"uvIndex":0,"weatherCode":1001,"precipitationProbability":0,"precipitationType":0,"sunriseTime":"2021-12-13T13:30:00Z","sunsetTime":"2021-12-13T22:56:40Z","visibility":15,"cloudCover":100,"moonPhase":3}},{"startTime":"2021-12-14T05:00:00Z","values":{"temperature":53.22,"temperatureMin":53.22,"temperatureMax":53.22,"temperatureApparent":53.22,"windSpeed":14.65,"windDirection":182.49,"humidity":57.03,"pressureSeaLevel":30.07,"uvIndex":0,"weatherCode":1001,"precipitationProbability":0,"precipitationType":0,"sunriseTime":"2021-12-13T13:30:00Z","sunsetTime":"2021-12-13T22:56:40Z","visibility":15,"cloudCover":100,"moonPhase":3}},{"startTime":"2021-12-14T06:00:00Z","values":{"temperature":53.64,"temperatureMin":53.64,"temperatureMax":53.64,"temperatureApparent":53.64,"windSpeed":14.09,"windDirection":180.71,"humidity":64.04,"pressureSeaLevel":30.06,"uvIndex":0,"weatherCode":1001,"precipitationProbability":0,"precipitationType":0,"sunriseTime":"2021-12-14T13:30:00Z","sunsetTime":"2021-12-14T22:56:40Z","visibility":15,"cloudCover":100,"moonPhase":3}},{"startTime":"2021-12-14T07:00:00Z","values":{"temperature":53.56,"temperatureMin":53.56,"temperatureMax":53.56,"temperatureApparent":53.56,"windSpeed":13.62,"windDirection":182.2,"humidity":73.92,"pressureSeaLevel":30.05,"uvIndex":0,"weatherCode":1001,"precipitationProbability":0,"precipitationType":0,"sunriseTime":"2021-12-14T13:30:00Z","sunsetTime":"2021-12-14T22:56:40Z","visibility":15,"cloudCover":100,"moonPhase":3}},{"startTime":"2021-12-14T08:00:00Z","values":{"temperature":54.09,"temperatureMin":54.09,"temperatureMax":54.09,"temperatureApparent":54.09,"windSpeed":12.5,"windDirection":184.66,"humidity":82,"pressureSeaLevel":30.06,"uvIndex":0,"weatherCode":1001,"precipitationProbability":0,"precipitationType":0,"sunriseTime":"2021-12-14T13:30:00Z","sunsetTime":"2021-12-14T22:56:40Z","visibility":15,"cloudCover":100,"moonPhase":3}},{"startTime":"2021-12-14T09:00:00Z","values":{"temperature":54.36,"temperatureMin":54.36,"temperatureMax":54.36,"temperatureApparent":54.36,"windSpeed":12.17,"windDirection":183.22,"humidity":88.26,"pressureSeaLevel":30.05,"uvIndex":0,"weatherCode":1001,"precipitationProbability":0,"precipitationType":0,"sunriseTime":"2021-12-14T13:30:00Z","sunsetTime":"2021-12-14T22:56:40Z","visibility":15,"cloudCover":100,"moonPhase":3}},{"startTime":"2021-12-14T10:00:00Z","values":{"temperature":54.32,"temperatureMin":54.32,"temperatureMax":54.32,"temperatureApparent":54.32,"windSpeed":11.86,"windDirection":187.66,"humidity":92.68,"pressureSeaLevel":30.04,"uvIndex":0,"weatherCode":1001,"precipitationProbability":0,"precipitationType":0,"sunriseTime":"2021-12-14T13:30:00Z","sunsetTime":"2021-12-14T22:56:40Z","visibility":15,"cloudCover":98.35,"moonPhase":3}}]}]
